{
  "qid": "141",
  "query": "Human Exploration",
  "rank": 2,
  "docid": 5885476,
  "coef": {
    "major": 0.0,
    "list": 0.0,
    "earli": -0.0,
    "europ": 0.0,
    "spanish": 0.0,
    "chronolog": 0.0,
    "includ": 0.9067426592071719,
    "histori": 0.0,
    "event": 0.0846023818560132,
    "ag": 0.0,
    "america": -0.0,
    "land": 0.0,
    "road": 0.0,
    "see": 0.0,
    "signific": 0.0,
    "china": 0.0,
    "prehistori": 0.0,
    "slaveri": 0.0,
    "ancient": 0.0,
    "human": 0.7921585986374968,
    "across": 0.0,
    "initi": 0.5418853677138515,
    "sea": 0.48124380567076563,
    "great": 0.08330631305272693,
    "european": -0.0,
    "britain": 1.7584097777313008e-16,
    "treati": 0.0,
    "treasur": 0.0,
    "colon": 0.0,
    "explor": 0.6554302955397517,
    "indian": 0.0,
    "migrat": 0.0,
    "columbu": 0.0,
    "settlement": 0.0,
    "voyag": 0.5973865671702673,
    "navig": 0.4059379617521534,
    "naval": 0.0,
    "exchang": -0.0,
    "subsequ": 0.7710772575193233,
    "asia": -0.0,
    "chines": 0.0,
    "christoph": 0.0,
    "discoveri": 0.6626639985494315,
    "africa": 0.0,
    "ireland": 0.27631662256368156,
    "incomplet": 0.7474434792173354,
    "silk": 0.0,
    "timelin": 0.35109594301355984,
    "portugues": 0.0,
    "submerg": 0.2436780520186016,
    "maritim": 0.32160458506196715,
    "columbian": -0.0,
    "ming": 0.0,
    "polynesian": 0.0,
    "tordesilla": 0.0
  }
}