{
  "qid": "1050241",
  "query": "who sang the song crazy arms",
  "rank": 4,
  "docno": "5410565-sw-suffix-1",
  "coef": {
    "show": 0.0,
    "more": 0.0,
    "ok": 0.0,
    "so": 0.0,
    "everyone": 0.0,
    "or": 0.17943697502056552,
    "some": 0.0,
    "of": 0.0,
    "you": 0.0,
    "might": -0.0,
    "have": -0.0,
    "heard": -0.0,
    "jay-z's": -0.0,
    "kingdom": -0.0,
    "come": -0.0,
    "album.": 0.0,
    "on": 0.0,
    "that": 0.0,
    "album": 0.14112555897147644,
    "he": 0.0,
    "has": 0.0,
    "a": 0.0,
    "song": 0.3815846419006508,
    "called": -0.0,
    "i": 0.0,
    "just": -0.0,
    "died": -0.0,
    "in": 0.0,
    "your": 0.0,
    "arms.": 0.4706728232027239,
    "but": 0.0,
    "there": 0.0805091325902098,
    "is": 0.10878100953620898,
    "an": 0.0,
    "original": 0.0,
    "version,": 0.007560724122214683,
    "the": 0.15347308317146566,
    "girl": 0.0,
    "backround.": 0.0,
    "im": 0.08454902815684671,
    "guessing": 0.0,
    "shes": 0.0,
    "from": 0.0,
    "80s?": -0.0,
    "dont": -0.0,
    "know.": 0.0,
    "know": 0.0,
    "remade": 0.298955302760192,
    "if": 0.0,
    "do": 0.0,
    "who": 0.0,
    "sang": 0.7892223453723803,
    "original,": 0.0,
    "please": 0.10337260411566145,
    "tell": 0.16289480176932478,
    "me.": 0.0,
    "stroopwafel": 0.059942409453888
  }
}