{
  "qid": "121",
  "query": "Racquet Sports",
  "rank": 2,
  "docid": 468141,
  "coef": {
    "state": 0.0,
    "north": 0.0,
    "bodi": 6.3803649884887195,
    "american": 0.0,
    "govern": 0.0678103877422245,
    "citi": 0.0,
    "new": 0.0,
    "extern": 0.0,
    "unit": 3.6048250300197373,
    "member": -0.0,
    "canada": -0.0,
    "associ": 3.2427475458374975,
    "link": 4.145099178736592,
    "chicago": -0.12530969526236554,
    "sport": 0.0,
    "philadelphia": 0.0,
    "york": 3.760745165833959,
    "tenni": 3.315438992423674,
    "boston": -0.025843131420550523,
    "club": 0.0,
    "detroit": -3.793947848818303e-17,
    "racket": 0.0,
    "racquet": 3.5099853696753742,
    "montreal": 0.0,
    "tuxedo": 0.0
  }
}