{
  "qid": "148",
  "query": "Tea",
  "rank": 4,
  "docid": 838934,
  "coef": {
    "aspect": 0.0003128231684326622,
    "blend": 0.0,
    "origin": 0.7724519042828778,
    "cultur": 0.4411338192304062,
    "seen": 0.0,
    "can": 0.5057603651365623,
    "emphasi": 0.0,
    "led": 0.0,
    "countri": 0.0,
    "classic": 1.1840231548447164e-16,
    "includ": -0.0,
    "histori": -0.0,
    "educ": 0.0,
    "21st": 0.0,
    "art": 0.34200752350245145,
    "develop": 0.6615377936720466,
    "popular": 0.35667063736508725,
    "singl": 0.0,
    "flourish": 0.0,
    "tradition": 0.6469291933966201,
    "root": 0.0,
    "common": -0.0,
    "influenc": 0.0,
    "institut": 0.0,
    "place": 0.0,
    "see": 0.0,
    "inform": 0.48815985366470227,
    "china": 0.0,
    "gain": 0.533938860660309,
    "japanes": 0.0,
    "resurg": -0.0,
    "make": 0.2783696465833682,
    "social": 0.8555350640019858,
    "centuri": 0.0,
    "extens": 0.611941689213417,
    "tradit": 0.0,
    "studi": 0.5989334515267345,
    "promin": 0.26482765939008607,
    "refer": 0.4149324142776447,
    "back": 0.25292835318399276,
    "technolog": -0.0,
    "especi": -0.0,
    "consumpt": 0.0,
    "experienc": -0.0,
    "high": 0.0,
    "trace": 0.4849389004215268,
    "research": 0.0,
    "old": 0.11398596404021014,
    "qualiti": 0.0,
    "climat": -0.0,
    "bubbl": 0.35702431184013345,
    "western": 0.0,
    "mountain": 0.0,
    "flower": 0.5724952437124878,
    "shop": -0.0,
    "landscap": 0.0,
    "uniqu": 0.0,
    "district": 0.0,
    "island": 0.0,
    "station": 1.5241162261587498e-05,
    "ceremoni": 0.0,
    "plantat": 0.0,
    "man": 0.0,
    "invent": 0.0,
    "commerc": 0.0,
    "dri": 0.34519097583680763,
    "chines": 0.19731879556729104,
    "spur": 0.03229122157247062,
    "tea": 0.5747214928316702,
    "cha": 0.003596096213520964,
    "cuisin": 0.0,
    "drink": 0.007880945287543652,
    "kong": -0.14972458677088343,
    "petal": 0.00014271475245800547,
    "hong": -7.406491299123317e-05,
    "taiwan": 0.06151608833891431,
    "calligraphi": 0.0,
    "yu": -0.0,
    "incens": 0.0,
    "stamen": 0.0,
    "lu": -0.0,
    "taiwanes": 0.6018048500856908,
    "xun": 0.0002975462769631356,
    "teahous": 0.0,
    "tatung": 3.139226518616736e-05,
    "oolong": -0.0,
    "gongfu": -0.09553401311699908,
    "laoren": 0.0,
    "pinglin": 0.0
  }
}