{
  "qid": "137",
  "query": "Online Companies",
  "rank": 9,
  "docid": 5128991,
  "coef": {
    "5": 0.16098548581462774,
    "lead": 0.0,
    "market": 0.0,
    "peopl": 0.15388691345552905,
    "emerg": 0.0,
    "nation": 0.0,
    "golden": -0.0,
    "platform": 0.0,
    "industri": 0.0,
    "us": -0.0,
    "acquir": 0.0,
    "core": 0.0,
    "servic": 0.0,
    "manag": 0.5808697136893493,
    "world": -0.0,
    "hold": 0.0,
    "oper": -0.0,
    "best": 0.2685898815782343,
    "establish": 0.0,
    "follow": 0.32994378999069246,
    "digit": 0.0379175447687011,
    "second": 0.0,
    "choic": 0.007134957643739131,
    "popular": 0.41589676766267525,
    "plai": 0.0073857380407077716,
    "publish": 0.17753644837397597,
    "local": 0.25755398089844456,
    "english": 0.020176425696501667,
    "free": 0.0,
    "capit": 0.0059006079509582995,
    "posit": 0.11076201307373833,
    "first": 0.0,
    "web": 0.0,
    "share": 0.0,
    "paid": 0.0,
    "base": 0.0,
    "achiev": 0.0,
    "success": 0.0,
    "softwar": 0.0,
    "combin": 0.11185463412455277,
    "global": 0.0,
    "2008": 0.23302415573099755,
    "technolog": 0.0,
    "ultim": 0.0,
    "onlin": 0.4213026372519004,
    "2": -0.0,
    "million": 0.0,
    "year": 0.13711494970071464,
    "incorpor": 0.36328218586232774,
    "payment": 0.22475512867354344,
    "2013": 0.2237000472898571,
    "grant": 0.0,
    "quickli": 0.0,
    "game": 0.3963931493816467,
    "10": 0.0,
    "survei": 0.0,
    "account": 0.0,
    "integr": 0.0,
    "comprehens": 0.0,
    "2012": 0.12421776498104632,
    "2010": 0.023112187350439108,
    "2007": 0.16342217065718131,
    "2005": 0.02456835482277454,
    "3": 8.5353525027436e-06,
    "water": 0.0,
    "margin": 0.057143488940893494,
    "top": -0.0,
    "mainli": 0.0,
    "statu": 0.0,
    "battl": 0.0,
    "sport": 0.0006765976513674997,
    "item": 0.005813915597651463,
    "shop": 0.0,
    "san": 0.00027951624996813554,
    "novemb": 0.0,
    "entertain": 0.0,
    "2011": 0.0,
    "2006": 0.5966793992284736,
    "registr": 0.0,
    "2009": -0.0,
    "compani": 0.4599139658577593,
    "subsidiari": 0.0,
    "facil": 0.0,
    "monei": -0.0,
    "captur": 0.0,
    "1st": 0.00012149307719577679,
    "oracl": 0.0,
    "virtual": 0.00013719812636048658,
    "raid": 9.362571374388146e-05,
    "favorit": -0.0,
    "partner": -0.0,
    "titl": 0.0,
    "fulfil": 0.0,
    "excel": -0.0,
    "kingdom": 0.0,
    "asia": 0.0,
    "award": 0.393493689685766,
    "premier": 0.0,
    "winner": 0.0246347142399996,
    "brand": 0.0,
    "sector": 0.0,
    "player": 0.0,
    "solut": 0.0,
    "databas": 0.0,
    "fifa": 0.15898994493757299,
    "simul": 0.0,
    "eagl": 0.0,
    "server": 0.5845398878902702,
    "thailand": 0.0,
    "malaysia": 0.501535632048258,
    "cart": 0.22714673350934045,
    "mol": 0.48059680948477246,
    "wholli": 0.0521029369954691,
    "ict": 0.0,
    "backup": 0.40181511818017157,
    "msc": 0.0,
    "multimedia": 0.0,
    "decent": 0.0,
    "malaysian": 0.09745791023115802,
    "ea": 0.024550650879489946,
    "casual": 0.07749904602974873,
    "fu": -0.0,
    "myr": 0.1367012955826392,
    "kung": -0.0,
    "vm": 0.0,
    "login": 0.0,
    "mmorpg": 0.2369962760438607,
    "vmware": 0.0,
    "3c": 0.0,
    "sdn": 0.27532419212060477,
    "bhd": 9.459240908656686e-18,
    "berhad": -0.0,
    "mmo": 0.025044017473972762,
    "cnx": 0.0,
    "mmog": 0.0,
    "gameaxi": -0.0,
    "accessport": -0.0,
    "war2": -0.0,
    "pikom": 0.0,
    "mycnx": 0.2834184000363777,
    "boomz": 0.4683403674588417
  }
}