{
  "qid": "134",
  "query": "Botany",
  "rank": 7,
  "docid": 6242281,
  "coef": {
    "system": 0.09447271611439986,
    "north": -0.0,
    "connect": 0.0,
    "public": 0.0,
    "wider": 0.0,
    "began": 0.0,
    "due": 0.5011310729120151,
    "town": 0.01171626823585317,
    "complet": 0.0,
    "citi": 0.0,
    "plan": 0.0,
    "central": 0.0,
    "new": 1.0600475448144753,
    "part": 0.0,
    "locat": 1.515037345709577,
    "improv": 0.0,
    "2018": -0.0,
    "centr": 0.7878075559852957,
    "suburb": 2.389895708069826,
    "south": 1.3742175045832048,
    "airport": 0.0,
    "eastern": 0.0,
    "transport": 1.3811014541314308,
    "rapid": 0.0,
    "botani": 1.5791978411019696,
    "programm": 2.137964969269934,
    "zealand": 1.0515530829483672,
    "2025": 1.4841089709817123,
    "auckland": 2.5196857925425262,
    "buswai": 0.0
  }
}