{
  "qid": "122",
  "query": "Monarchy",
  "rank": 3,
  "docid": 2546312,
  "coef": {
    "be": 0.0,
    "state": 0.06168848644352134,
    "major": 0.0,
    "legitimaci": 0.10534753729183685,
    "union": 0.0,
    "action": 0.0,
    "right": 0.13009147816761912,
    "exist": -0.0,
    "seen": 0.0,
    "attempt": 0.0,
    "can": 0.0,
    "return": 0.008125576583936332,
    "system": 0.0,
    "earli": 0.0,
    "debat": 0.33297991784091246,
    "europ": 0.03832382001215715,
    "freedom": 0.0,
    "countri": 0.22311378036703922,
    "movement": 0.1259283824863727,
    "revolut": 0.22846485926358578,
    "divin": 0.0,
    "us": 0.0,
    "begin": 0.0,
    "confeder": 0.0,
    "concept": 0.0,
    "taken": 0.0,
    "gener": 0.20257477671652419,
    "target": 0.0,
    "includ": 0.0,
    "prevent": 0.0,
    "head": 0.0,
    "challeng": 0.23147690153445324,
    "histori": 0.0,
    "take": 0.0526099393939286,
    "attent": 0.0,
    "call": 0.2805134800752935,
    "polit": 0.0,
    "legal": 0.30561826034602585,
    "french": 0.22940507233369423,
    "form": 0.14273119463200964,
    "civil": 0.10161294378982166,
    "expand": 0.0,
    "world": 0.0966053819567735,
    "hold": 0.0,
    "bodi": 0.058593757924702616,
    "principl": 0.0,
    "ag": 0.18576839415680338,
    "involv": 0.0,
    "still": 0.0,
    "abil": 0.0,
    "follow": 0.0,
    "charg": 0.0,
    "critic": 0.14381947308124127,
    "american": 0.0,
    "control": 0.0,
    "elimin": 0.0,
    "second": 0.0,
    "expens": 0.0,
    "carri": 0.0,
    "govern": 0.0,
    "perceiv": 0.0,
    "issu": 0.0,
    "aim": 0.0,
    "feder": 0.151100007704677,
    "canadian": 0.0,
    "suppress": 0.010588970823756453,
    "citi": 0.0,
    "democrat": 0.0,
    "act": 0.04014766117872069,
    "exampl": 0.0,
    "abl": 0.0,
    "time": 0.0,
    "protest": 0.04639588394956583,
    "down": 0.0,
    "notabl": 0.0721697615367538,
    "symbol": 0.0,
    "end": 0.0,
    "institut": 0.0,
    "relat": 0.0,
    "argument": 0.0,
    "place": 0.0,
    "franc": 0.0,
    "see": 0.0,
    "consid": 0.0,
    "local": 0.0,
    "express": 0.0,
    "english": 0.0,
    "saw": 0.0,
    "constitut": 0.0,
    "equal": 0.0,
    "20": 0.0,
    "specif": 0.0,
    "known": 0.0,
    "expel": 0.0,
    "histor": 0.0,
    "russia": 0.0,
    "spain": 0.2607868314839145,
    "republican": 0.055182047264128,
    "intern": 0.0,
    "terrorist": 0.0,
    "pave": 0.0026336718713215503,
    "first": 0.0,
    "abolit": 0.0,
    "empir": 0.0,
    "offici": 0.06665404672287943,
    "enlighten": 0.0,
    "war": 0.304291736815232,
    "wai": 0.04353711539820204,
    "unit": 0.3878259501712864,
    "releas": 0.0,
    "centuri": 0.14073986725177917,
    "monarchi": 0.4303623797308122,
    "council": 0.0,
    "dai": 0.0,
    "achiev": 0.0,
    "replac": 0.0,
    "realm": 0.0,
    "canada": 0.0,
    "declar": 0.19699459434259822,
    "dictatorship": 0.0,
    "associ": 0.39999042288082987,
    "power": 0.0,
    "hous": 0.0,
    "2008": 0.0,
    "modern": 0.0,
    "occur": 0.0,
    "human": 0.0,
    "petit": -0.0,
    "absolut": 0.06756610673865182,
    "greater": 0.0,
    "initi": 0.0,
    "present": 0.0,
    "uk": 0.0,
    "sign": 0.0,
    "case": 0.0,
    "year": 0.0,
    "revers": -0.0,
    "popul": 0.0,
    "univers": 0.0,
    "grant": 0.0,
    "trial": 0.0,
    "speech": 0.0,
    "famili": 0.03346725324895147,
    "substanti": 0.0,
    "select": 0.0,
    "restrict": 0.0,
    "speak": 0.0,
    "frequent": 0.0,
    "degre": 0.0,
    "2012": 0.11494878818903778,
    "al": 0.4050657762847417,
    "european": 0.0,
    "circl": 0.0,
    "provinc": 0.0,
    "elect": 0.0,
    "hundr": 0.0,
    "held": 0.0,
    "17": 0.0,
    "lobbi": 0.0,
    "republ": 0.0,
    "august": 0.0,
    "crimin": 0.21055626500723615,
    "affair": 0.0,
    "treati": 0.0,
    "vote": 0.07743622018777001,
    "2011": 0.09780558423212696,
    "legisl": 0.0,
    "charter": 0.0,
    "loyalist": 0.0,
    "restor": 0.0,
    "decid": 0.10493861360790366,
    "twentieth": 0.0,
    "juli": 0.0,
    "enact": 0.0,
    "februari": 0.2801711351443051,
    "pass": 0.0,
    "1867": 0.0,
    "settlement": 0.04981719843979776,
    "march": 0.0,
    "king": 0.0,
    "earlier": 0.0,
    "appoint": 0.0,
    "thursdai": 0.0,
    "highlight": 0.0,
    "oath": 0.010291280399196518,
    "stuart": 0.0,
    "sovereignti": 0.0,
    "japan": 0.08560330352632568,
    "raid": 0.0,
    "brief": 0.13811355512182627,
    "sovereign": 0.3336480751958136,
    "defens": 0.0,
    "bloodi": 0.0,
    "launch": 0.0,
    "contenti": 0.0,
    "patriot": 0.08685034007395104,
    "prison": 0.0,
    "titl": 0.0,
    "contest": 0.05431352784091744,
    "proclam": -0.0,
    "elitist": 0.0,
    "fundament": 0.0,
    "arab": 0.0,
    "royal": 0.31990502997954917,
    "kingdom": 0.0,
    "vatican": 0.0,
    "transmiss": -0.0,
    "franco": -0.0,
    "night": 0.0,
    "birthdai": 0.0,
    "interior": 0.0,
    "dissent": 0.0,
    "acceler": 0.0,
    "heir": 0.05351279950241806,
    "norwai": 0.0,
    "stronger": 0.0,
    "incompat": 0.0,
    "1917": 0.0,
    "pearl": 0.0,
    "morocco": 0.0,
    "unfair": 0.0,
    "protestor": 0.0,
    "underli": 0.0,
    "emir": 0.0,
    "shia": 0.2008844138399728,
    "prime": 0.0,
    "arabia": 0.16083787448014533,
    "moham": 0.00902369863293783,
    "parliament": 0.2740731437487033,
    "khalifa": 0.0,
    "minist": 0.34514079352323856,
    "commonwealth": 0.0,
    "vi": 0.00639854068919539,
    "belgium": 0.056058405923616904,
    "swedish": 0.0,
    "chant": 0.0,
    "netherland": 0.0,
    "belgian": 0.0,
    "prerog": 0.0,
    "deadli": 0.0,
    "crown": 0.16366508503593635,
    "advisor": 0.0,
    "thailand": 0.0,
    "malaysia": 0.016748783325441947,
    "monarch": 0.24109327448472992,
    "monaco": 0.009295386220896392,
    "slogan": 0.0,
    "curtail": 0.0,
    "sweden": 0.0,
    "saudi": 0.02757728373836922,
    "citizenship": 0.08295208158707087,
    "qu": 0.0,
    "bec": 0.0,
    "se": 0.0,
    "majest": 0.0,
    "butcher": 0.0,
    "bahrain": 0.0,
    "qatar": 0.0,
    "brunei": 0.0,
    "oman": 0.0,
    "denmark": 0.0,
    "provinci": 0.0,
    "victoria": 0.23680949882272176,
    "bin": 0.0,
    "isa": 0.0,
    "coven": 0.0,
    "monarchist": 0.0,
    "manama": 0.0,
    "karin": 0.0,
    "liechtenstein": 0.0,
    "hereditari": 0.0,
    "luxembourg": 0.0,
    "1701": 0.059769802365876014,
    "privi": 0.18799109356379795,
    "swaziland": 0.0,
    "bourbon": 0.040252053735051224,
    "bahraini": 0.0,
    "roundabout": 0.0,
    "hamad": 0.0,
    "crackdown": 0.0,
    "saud": 0.0,
    "unaccount": 0.0,
    "undemocrat": 0.0,
    "nayef": 0.0,
    "postindepend": 0.0,
    "enstr": 0.0
  }
}