{
  "qid": "132",
  "query": "Literacy",
  "rank": 1,
  "docid": 1945678,
  "coef": {
    "state": 0.8965528044741902,
    "self": 0.0,
    "union": 0.0763122999100918,
    "inequ": 0.0,
    "religion": -0.0,
    "figur": 0.0,
    "differ": 0.0,
    "educ": -0.0,
    "follow": 0.0,
    "group": -0.0,
    "territori": 0.3187800329683631,
    "lack": 0.0,
    "recent": 0.0,
    "see": -0.0,
    "collect": 0.0,
    "accord": -0.0,
    "gender": 0.0,
    "social": -0.0,
    "mean": 0.0,
    "estim": 0.0,
    "total": -0.0,
    "tabl": 0.0,
    "show": 0.0,
    "percentag": -0.0,
    "rate": 0.23248812136672872,
    "data": 0.0,
    "femal": 0.0,
    "detail": 0.36741242209995006,
    "assess": 0.24446328186350053,
    "male": 0.027785719950108267,
    "essenti": 0.0,
    "2018": 0.0,
    "highest": 0.0,
    "lowest": 0.14212870437605288,
    "uneven": 0.0,
    "cast": 0.0,
    "censu": 0.0,
    "2011": 0.6419438882667853,
    "43": 0.0,
    "literaci": 0.7526527436468297,
    "alt": -0.18435803343840662,
    "252": -0.0,
    "pp": 0.0,
    "1951": 0.0,
    "sfn": 0.0,
    "india": 0.34421313877504345,
    "timelin": 0.0,
    "kerala": 0.0,
    "taker": 0.0,
    "bihar": 0.0,
    "lakshadweep": 0.6496429029099088,
    "rajasthan": 0.0,
    "nso": 0.0
  }
}