{
  "qid": "124",
  "query": "Charity",
  "rank": 2,
  "docid": 2893143,
  "coef": {
    "state": 0.0,
    "mai": 0.0,
    "act": 0.567537065263866,
    "collect": 0.0,
    "new": 6.447739753072215e-05,
    "unit": 0.431097981999201,
    "refer": 0.0,
    "canada": 0.26118896617304066,
    "medic": -0.0,
    "2005": 0.0330495392782294,
    "hospit": 0.0,
    "fund": 0.0,
    "edward": 0.0,
    "2006": 0.15708589833529693,
    "2001": 0.0,
    "2009": -0.0,
    "island": 0.6164503226748708,
    "1978": 0.1307055963790132,
    "princ": -0.0,
    "1922": -0.0,
    "kingdom": 0.0,
    "2020": 0.0,
    "australia": 0.6620256172069766,
    "1988": -0.0,
    "1958": -0.0,
    "chariti": 0.44785886468635155,
    "1979": -0.0,
    "recreat": 0.0,
    "ireland": -0.0,
    "zealand": 0.0,
    "tasmania": 0.0,
    "queensland": 0.0,
    "singapor": 0.0,
    "barbado": -0.0,
    "victoria": 0.0
  }
}