{
  "qid": "149",
  "query": "Public Transport",
  "rank": 9,
  "docid": 3002984,
  "coef": {
    "state": 0.0,
    "organis": 0.2353734541296867,
    "system": 0.0,
    "mai": 0.038743190122611904,
    "nation": 0.2060102314478257,
    "region": 0.17564156807436926,
    "name": 0.054880195852286325,
    "daili": 0.0,
    "evalu": 0.0,
    "countri": 0.0,
    "product": 0.0,
    "us": 0.0,
    "confeder": 0.0,
    "core": 0.03934234043121215,
    "public": 0.0,
    "servic": 0.267595662890854,
    "includ": 0.0,
    "histori": 0.0,
    "number": 0.0,
    "oper": 0.18168475760075975,
    "open": -0.0,
    "area": 0.020350121828535548,
    "bodi": 0.0,
    "ad": 0.0,
    "establish": 0.0,
    "kei": 0.0,
    "formal": 0.0,
    "follow": 0.0,
    "octob": 0.0688771311569237,
    "england": 0.0,
    "electron": 0.0,
    "creation": 0.051180521068015364,
    "onc": 0.0,
    "develop": 0.0,
    "govern": 0.0,
    "portal": 0.19376280348769306,
    "close": 0.0,
    "group": 0.0,
    "opinion": 0.0,
    "author": -0.0,
    "ident": 0.01196504243559546,
    "place": 0.03334097111987502,
    "1999": 0.0,
    "local": 0.2324867847554435,
    "collect": 0.0,
    "northern": 0.0,
    "direct": 0.0,
    "inform": 0.0008591850726449317,
    "structur": 0.0,
    "offici": 0.0,
    "part": 0.0,
    "releas": 0.0,
    "basi": 0.03111419069382405,
    "council": 0.0,
    "success": 0.0,
    "execut": 0.0,
    "associ": 0.0,
    "travel": 0.0,
    "uk": 0.24311531941755135,
    "year": 0.0,
    "request": 0.0,
    "model": 0.0,
    "indic": 0.0,
    "boundari": 0.03556547041675797,
    "schedul": 0.0,
    "maintain": 0.0,
    "data": -0.0,
    "detail": 0.0,
    "coordin": 0.0,
    "mode": 0.0,
    "divid": 0.0,
    "updat": 0.0,
    "comprehens": 0.13895595052745785,
    "consist": -0.0,
    "2016": 0.0,
    "2014": 0.17163246153830378,
    "2010": 8.277836241222509e-06,
    "2000": 0.031187643680739046,
    "welsh": 0.0,
    "great": 0.0,
    "2003": 0.0,
    "2004": 0.0,
    "britain": 0.0,
    "assembl": 0.05646964149404934,
    "brown": 0.0,
    "london": -0.0,
    "rail": 0.0,
    "prepar": 0.0599447609058053,
    "counti": 0.025438313506672944,
    "novemb": 0.0,
    "decemb": 0.07380208047094523,
    "registr": 0.0,
    "offic": 0.0,
    "septemb": 0.0,
    "bu": 0.03652021439722953,
    "depart": 0.0,
    "secretari": 0.0,
    "destin": 0.0,
    "passeng": 0.0,
    "vehicl": 0.0,
    "rout": 0.0,
    "31": 0.0,
    "agenc": 0.0,
    "announc": 0.0,
    "pass": 0.1215877362252059,
    "stop": 0.0,
    "access": 0.0,
    "transport": 0.18728155138825503,
    "map": 0.20875690911827285,
    "march": 0.0,
    "purpos": 0.0,
    "launch": 0.0,
    "deliveri": 0.0,
    "appl": 0.0,
    "door": 0.0,
    "partnership": 0.0,
    "gordon": 0.09954828336792237,
    "weekli": 0.0,
    "prime": 1.0957907867044445e-15,
    "databas": 0.0,
    "alistair": 0.0,
    "minist": 5.923193441645645e-17,
    "prototyp": 0.0,
    "ireland": 0.0,
    "scottish": 0.0,
    "journei": 0.04497149455865069,
    "node": 0.0,
    "imparti": 0.0,
    "googl": 0.0,
    "repositori": -0.0,
    "stakehold": 0.0,
    "planner": 0.19172678584839728,
    "advisori": 0.07044626343598519,
    "gov": -0.0,
    "darl": 0.0,
    "gazett": 0.0,
    "lancashir": 0.0,
    "dataset": 0.13724180451693915,
    "travelin": 0.17561154170005683,
    "translink": 0.0,
    "openstreetmap": 0.0,
    "naptan": 0.11725608212887648,
    "mysocieti": 0.0,
    "transxchang": 0.03383117283922683,
    "mapument": 0.0
  }
}