{
  "qid": "127",
  "query": "Clergy",
  "rank": 4,
  "docid": 205338,
  "coef": {
    "state": 0.0,
    "religion": 0.0,
    "benefit": 0.0,
    "exist": 0.0,
    "north": 0.0,
    "tendenc": 0.0,
    "mai": -0.0,
    "nation": 0.0,
    "name": 0.021561232652488167,
    "difficult": 0.0,
    "countri": 0.25609072466972815,
    "spanish": 0.0,
    "next": 0.0,
    "middl": 0.0,
    "acquir": 0.0,
    "gener": 0.162301288638094,
    "includ": 0.0,
    "word": 0.16189190271782078,
    "call": 0.0,
    "allow": 0.0,
    "number": 0.06030925129133909,
    "import": 0.0,
    "normal": 0.0,
    "commonli": 0.0,
    "term": 0.23218181816102088,
    "vari": 0.0,
    "american": 0.0,
    "church": 0.2503931103297164,
    "england": 0.0,
    "long": 0.0,
    "interest": 0.0,
    "cathol": 0.0,
    "well": 0.0,
    "far": 0.0,
    "reform": 0.0,
    "close": 0.0,
    "commun": 0.0,
    "tradition": 0.0,
    "academ": 0.0,
    "abl": 0.018102324014852088,
    "rank": 0.0,
    "common": 0.11846895177052558,
    "function": 0.0,
    "see": -0.0,
    "non": 0.0,
    "live": 0.04800760321690345,
    "local": 0.05681316548013684,
    "specif": 0.0,
    "known": 0.0,
    "direct": 0.0,
    "inform": 0.0,
    "histor": 0.0,
    "move": 0.0,
    "practic": 0.0,
    "class": 0.0,
    "first": 0.0,
    "part": 0.0,
    "properti": 0.05091123929216964,
    "unit": 0.19074180779759306,
    "centuri": 0.0,
    "1896": 0.0,
    "person": 0.0,
    "roman": 0.0,
    "hous": 0.22249311876067127,
    "especi": 0.1872008977508139,
    "serv": 0.0,
    "level": 0.0,
    "partli": 0.0,
    "greater": 0.0,
    "case": 0.0,
    "depend": 0.0,
    "consider": 0.0,
    "old": 0.0042603151242983734,
    "maintain": 0.0,
    "univers": 0.0,
    "typic": -0.0,
    "now": 0.24784990307424168,
    "locat": 0.0,
    "10": 0.0,
    "famili": 0.0,
    "frequent": 0.0,
    "modest": 0.0,
    "occup": 0.0,
    "home": 0.1993285151112472,
    "proport": 0.0,
    "smaller": 0.0,
    "near": 0.0,
    "addit": 0.04514647048767023,
    "upper": 0.0,
    "least": 0.0,
    "britain": 0.0,
    "14th": 0.0,
    "west": 0.0,
    "convent": 0.0,
    "administr": 0.0,
    "museum": 0.0,
    "isl": 0.0,
    "resid": 0.1880058001092337,
    "presbyterian": 0.0,
    "sold": 0.0,
    "offic": 0.03266160175611493,
    "methodist": 0.0,
    "denomin": 0.1352843291720161,
    "trust": 0.0,
    "congreg": 0.0,
    "baptist": 0.0,
    "southern": 0.0,
    "british": 0.0,
    "1861": 0.0,
    "1820": 0.0,
    "purchas": 0.0,
    "mansion": 0.0,
    "titl": 0.13404375521734896,
    "massachusett": 0.0,
    "priori": -0.0,
    "exchang": 0.0,
    "palac": 0.0,
    "kingdom": 0.0,
    "transfer": 0.0,
    "fashion": 0.0,
    "canon": 0.0,
    "comfort": 0.0,
    "ruin": 0.0,
    "chapel": 0.0,
    "galleri": -0.0,
    "grand": 0.0,
    "bishop": 0.0,
    "salari": 0.0,
    "minist": 0.0,
    "commonwealth": 0.0,
    "cognat": 0.0,
    "ireland": 0.0,
    "ordinari": 0.0,
    "priest": 0.21999638589462292,
    "scotland": 0.0,
    "scottish": 0.0,
    "villag": 0.0,
    "lieu": 0.0,
    "interv": 0.0,
    "parish": 0.16227525769840712,
    "anglican": 0.04381686520322888,
    "ecclesiast": 0.0,
    "parochi": -0.0,
    "nomenclatur": 0.035678205821167,
    "usual": 0.0,
    "dean": 0.0,
    "communion": 0.0,
    "philippin": 0.010955638501155152,
    "parson": 0.0,
    "lutheran": 0.0,
    "clergi": 0.0816248175332412,
    "mans": 0.1336036533391091,
    "yorkshir": 0.0,
    "vicarag": 0.18610612304627983,
    "rectori": 0.1519240857089677,
    "conformist": 0.0,
    "deaneri": 0.0,
    "bront": 0.0,
    "calqu": 0.0,
    "rector": 0.2443099308797143,
    "presbyt": 0.0,
    "haworth": 0.0,
    "presbyteri": 0.0,
    "convento": 0.0,
    "parsonag": 0.08628260087588795,
    "canonri": 0.0,
    "alfriston": 0.0,
    "conservation": 0.0,
    "pastorium": 0.0
  }
}