{
  "qid": "106",
  "query": "Climate Change Activists",
  "rank": 5,
  "docid": 6175685,
  "coef": {
    "action": 0.0,
    "inspir": 0.48749682415625006,
    "nation": 0.0,
    "connect": -0.0,
    "countri": 0.0,
    "concern": 0.3392700922170555,
    "fight": 0.009210831982802675,
    "gener": 0.4926745351961571,
    "began": 0.5283494626556562,
    "take": 0.0,
    "word": 0.5071523634495999,
    "educ": 0.34196994773457723,
    "event": 0.45851198959371514,
    "bring": 0.0,
    "sever": 0.0,
    "kei": 0.38340360426084996,
    "school": 0.716530780215494,
    "follow": 0.0,
    "town": 0.43188601718940156,
    "work": 0.3559724019981646,
    "just": 0.550885870116537,
    "fit": 0.0,
    "youth": 0.39037059175569644,
    "chang": 0.0,
    "young": 0.0,
    "govern": 0.28777966947857525,
    "environment": 0.3691980838616836,
    "aim": 0.0,
    "commun": 0.0,
    "life": 0.0,
    "justic": 0.2656477234525,
    "strike": 0.0,
    "organ": 0.0,
    "notabl": 0.0,
    "student": 0.0,
    "will": 0.08365441717851874,
    "sexual": 0.14222028208909276,
    "non": 0.0,
    "contribut": 0.5409673373370738,
    "mention": 0.0,
    "intern": 0.0,
    "join": 0.05563298558742588,
    "who": 0.5243064753799803,
    "media": 0.4046066823651425,
    "activ": 0.0,
    "gender": 0.0,
    "littl": 0.012060760613067293,
    "activist": 0.0,
    "2008": 0.0,
    "mean": 0.011079243121915883,
    "increas": 0.0,
    "2": 0.0,
    "present": 0.0,
    "pattern": 0.416579849762437,
    "year": 0.0,
    "environ": 0.10161567053976336,
    "pollut": 0.0,
    "recognit": 0.5218463277297387,
    "000": 0.0,
    "face": 0.0,
    "health": 0.0,
    "unusu": 0.0,
    "old": 0.019159326598634403,
    "primari": 0.0,
    "repeatedli": 0.0,
    "worldwid": 0.0,
    "coordin": 0.0,
    "audienc": 0.0,
    "consequ": 0.0,
    "start": 0.0,
    "water": 0.00022189899820119986,
    "receiv": 0.0,
    "climat": 0.7541521523514741,
    "weather": 0.0,
    "knowledg": 0.0,
    "spoke": 0.0,
    "august": -0.0,
    "project": 0.178280279053007,
    "hail": 0.015420255374366518,
    "2019": 0.3111744604885963,
    "eleven": 0.0,
    "south": 0.01719568146778015,
    "demand": 0.0,
    "devast": 0.1515152334586558,
    "african": 0.0,
    "access": 0.6279572500421848,
    "born": 0.0,
    "march": 0.16367154801341224,
    "januari": 0.0,
    "polici": 0.0,
    "urg": 0.0,
    "township": 0.0,
    "profit": 0.0,
    "answer": 0.0,
    "am": 0.0,
    "crisi": 6.787396388814925e-05,
    "speaker": 0.027344520873589843,
    "volunt": 0.0,
    "reproduct": 0.0,
    "collabor": 0.0,
    "rubi": 0.0,
    "parallel": 0.0,
    "classroom": 0.3560396089897359,
    "africa": 0.5645885950752886,
    "parliament": 0.0,
    "mentor": 0.0,
    "keynot": 0.17198798027756962,
    "swedish": 0.0,
    "cape": 0.0,
    "greta": 0.0,
    "urgent": 0.0,
    "impoverish": 0.0,
    "sampson": 0.20079855875677838,
    "resili": 0.0,
    "symposium": 0.1802334850042042,
    "loom": 0.6351318060486892,
    "thunberg": 0.0,
    "zulu": 0.0,
    "johannesburg": 0.0,
    "ubuntu": 0.0,
    "yola": 0.0,
    "khayelitsha": 0.09681158876617904,
    "unfpa": 0.0,
    "kiara": 0.0102617728979923,
    "xoli": 0.0,
    "mgogwana": 0.386046700329375,
    "earthchild": 0.0,
    "nirghin": 0.4025237375548889,
    "fuyani": 0.0,
    "yolomela": 0.0
  }
}